ServeRmore.py
VERSION.py
srvl_config.py
serveRmore-0.1.2.data/scripts/README.md
serveRmore-0.1.2.data/scripts/srm
serveRmore-0.1.2.dist-info/LICENSE
serveRmore-0.1.2.dist-info/METADATA
serveRmore-0.1.2.dist-info/WHEEL
serveRmore-0.1.2.dist-info/top_level.txt
serveRmore-0.1.2.dist-info/RECORD
