Metadata-Version: 2.1
Name: serveRmore
Version: 0.1.2
Summary: Serve R more on Serverless.
Home-page: https://github.com/Origent/ServeRmore.git
Author: Origent Data Sciences
Author-email: cloudhosting@origent.com
License: Apache License 2.0
Platform: UNKNOWN
Classifier: Development Status :: 4 - Beta
Classifier: Environment :: Web Environment
Classifier: Programming Language :: Python :: 3
Classifier: Operating System :: MacOS :: MacOS X
Classifier: Operating System :: POSIX
Classifier: Intended Audience :: Developers
Classifier: Intended Audience :: System Administrators
Classifier: Topic :: Internet :: WWW/HTTP :: HTTP Servers
Classifier: Topic :: Scientific/Engineering :: Bio-Informatics
Requires-Python: >=3
Requires-Dist: PyYAML
Requires-Dist: boto3
Requires-Dist: paramiko
Requires-Dist: requests
